qoco_cuda.cpython-311-x86_64-linux-gnu.so
qoco_cuda-0.1.0.dist-info/METADATA
qoco_cuda-0.1.0.dist-info/WHEEL
qoco_cuda-0.1.0.dist-info/RECORD
qoco_cuda-0.1.0.dist-info/licenses/LICENSE
