Metadata-Version: 2.2
Name: qoco-cuda
Version: 0.1.0
Summary: QOCO: Quadratic Objective Conic Optimizer
Author-Email: "Govind M. Chari" <govindchari1@gmail.com>
Project-URL: Homepage, https://github.com/qoco-org/qoco
Project-URL: Issues, https://github.com/qoco-org/qoco/issues
Requires-Python: >=3.8
Requires-Dist: numpy>=1.7
Requires-Dist: scipy>=0.13.2
Requires-Dist: setuptools
Requires-Dist: qoco>=0.2.0
